sharpedge/__init__.py
sharpedge/_utils/utility.py
sharpedge/frame_image.py
sharpedge/modulate_image.py
sharpedge/pca_compression.py
sharpedge/pooling_image.py
sharpedge/reposition_image.py
sharpedge/seam_carving.py
sharpedge-1.1.15.dist-info/LICENSE
sharpedge-1.1.15.dist-info/METADATA
sharpedge-1.1.15.dist-info/WHEEL
sharpedge-1.1.15.dist-info/RECORD
