Metadata-Version: 2.3
Name: sharpedge
Version: 1.1.15
Summary: Collection of image processing tools and techniques, including padding, flipping, colorscale conversion, seam carving, and image shrinking. Designed for efficient manipulation and transformation of images.
License: MIT
Author: Jenny Zhang, Archer Liu, Inder Khera, Hankun Xiao
Requires-Python: >=3.11
Classifier: License :: OSI Approved :: MIT License
Classifier: Programming Language :: Python :: 3
Classifier: Programming Language :: Python :: 3.11
Classifier: Programming Language :: Python :: 3.12
Classifier: Programming Language :: Python :: 3.13
Requires-Dist: matplotlib (>=3.10.0,<4.0.0)
Requires-Dist: numpy (>=2.2.1)
Requires-Dist: pillow (>=11.1.0,<12.0.0)
Requires-Dist: scipy (>=1.15.1,<2.0.0)
